pythonic_fp/fptools/__init__.py
pythonic_fp/fptools/__init__.pyi
pythonic_fp/fptools/either.py
pythonic_fp/fptools/either.pyi
pythonic_fp/fptools/function.py
pythonic_fp/fptools/function.pyi
pythonic_fp/fptools/lazy.py
pythonic_fp/fptools/lazy.pyi
pythonic_fp/fptools/maybe.py
pythonic_fp/fptools/maybe.pyi
pythonic_fp/fptools/py.typed
pythonic_fp/fptools/state.py
pythonic_fp/fptools/state.pyi
pythonic_fp_fptools-5.2.0.dist-info/licenses/LICENSE
pythonic_fp_fptools-5.2.0.dist-info/WHEEL
pythonic_fp_fptools-5.2.0.dist-info/METADATA
pythonic_fp_fptools-5.2.0.dist-info/RECORD
