Metadata-Version: 2.4
Name: pythonic-fp-fptools
Version: 5.2.0
Summary: Pythonic FP - Functional Programming Tools
Keywords: either,fp,functional,functional programming,lazy,maybe,monad,non-strict
Author-email: "Geoffrey R. Scheller" <geoffrey@scheller.com>
Requires-Python: >=3.12
Classifier: Development Status :: 4 - Beta
Classifier: Framework :: Pytest
Classifier: Intended Audience :: Developers
Classifier: License :: OSI Approved :: Apache Software License
Classifier: Operating System :: OS Independent
Classifier: Programming Language :: Python :: 3.13
Classifier: Typing :: Typed
License-File: LICENSE
Requires-Dist: pythonic-fp-booleans>=2.1.1
Requires-Dist: pythonic-fp-circulararray>=6.0.1
Requires-Dist: pythonic-fp-gadgets>=4.0.2
Requires-Dist: pytest>=8.4.1 ; extra == "test"
Requires-Dist: pythonic-fp-containers>=4.0.1 ; extra == "test"
Requires-Dist: pythonic-fp-iterables>=5.1.3 ; extra == "test"
Requires-Dist: pythonic-fp-queues>=5.1.1 ; extra == "test"
Project-URL: Changelog, https://github.com/grscheller/pythonic-fp-fptools/blob/main/CHANGELOG.rst
Project-URL: Documentation, https://grscheller.github.io/pythonic-fp/fptools/development/build/html/
Project-URL: Homepage, https://grscheller.github.io/pythonic-fp/homepage/build/html/
Project-URL: Source, https://github.com/grscheller/pythonic-fp-fptools
Provides-Extra: test
